{"1":{"expressID":1,"type":2077209135,"Identification":null,"FamilyName":null,"GivenName":{"value":"","type":1,"name":"IFCLABEL"},"MiddleNames":null,"PrefixTitles":null,"SuffixTitles":null,"Roles":null,"Addresses":null},"2":{"expressID":2,"type":4251960020,"Identification":null,"Name":{"value":"","type":1,"name":"IFCLABEL"},"Description":null,"Roles":null,"Addresses":null},"3":{"expressID":3,"type":101040310,"ThePerson":{"value":1,"type":5},"TheOrganization":{"value":2,"type":5},"Roles":null},"4":{"expressID":4,"type":639542469,"ApplicationDeveloper":{"value":2,"type":5},"Version":{"value":"0.21 build 2","type":1,"name":"IFCLABEL"},"ApplicationFullName":{"value":"FreeCAD","type":1,"name":"IFCLABEL"},"ApplicationIdentifier":{"value":"118df2cf_ed21_438e_a41","type":1,"name":"IFCIDENTIFIER"}},"5":{"expressID":5,"type":1207048766,"OwningUser":{"value":3,"type":5},"OwningApplication":{"value":4,"type":5},"State":null,"ChangeAction":{"type":3,"value":"ADDED"},"LastModifiedDate":{"type":10,"name":"IFCTIMESTAMP","value":1722771575},"LastModifyingUser":{"value":3,"type":5},"LastModifyingApplication":{"value":4,"type":5},"CreationDate":{"type":10,"name":"IFCTIMESTAMP","value":1722771575}},"12":{"expressID":12,"type":2949456006,"LengthExponent":0,"MassExponent":0,"TimeExponent":0,"ElectricCurrentExponent":0,"ThermodynamicTemperatureExponent":0,"AmountOfSubstanceExponent":0,"LuminousIntensityExponent":0},"13":{"expressID":13,"type":448429030,"Dimensions":{"value":0,"type":5},"UnitType":{"type":3,"value":"LENGTHUNIT"},"Prefix":null,"Name":{"type":3,"value":"METRE"}},"14":{"expressID":14,"type":448429030,"Dimensions":{"value":0,"type":5},"UnitType":{"type":3,"value":"AREAUNIT"},"Prefix":null,"Name":{"type":3,"value":"SQUARE_METRE"}},"15":{"expressID":15,"type":448429030,"Dimensions":{"value":0,"type":5},"UnitType":{"type":3,"value":"VOLUMEUNIT"},"Prefix":null,"Name":{"type":3,"value":"CUBIC_METRE"}},"16":{"expressID":16,"type":448429030,"Dimensions":{"value":0,"type":5},"UnitType":{"type":3,"value":"PLANEANGLEUNIT"},"Prefix":null,"Name":{"type":3,"value":"RADIAN"}},"17":{"expressID":17,"type":2597039031,"ValueComponent":{"type":4,"name":"IFCPLANEANGLEMEASURE","value":0.017453292519943295},"UnitComponent":{"value":16,"type":5}},"18":{"expressID":18,"type":2889183280,"Dimensions":{"value":12,"type":5},"UnitType":{"type":3,"value":"PLANEANGLEUNIT"},"Name":{"value":"DEGREE","type":1,"name":"IFCLABEL"},"ConversionFactor":{"value":17,"type":5}},"19":{"expressID":19,"type":180925521,"Units":[{"value":13,"type":5},{"value":14,"type":5},{"value":15,"type":5},{"value":18,"type":5}]},"23":{"expressID":23,"type":103090709,"GlobalId":{"value":"1k0C6e7cr7tgjiH9zKWB9F","type":1,"name":"IFCGLOBALLYUNIQUEID"},"OwnerHistory":{"expressID":5,"type":1207048766,"OwningUser":{"expressID":3,"type":101040310,"ThePerson":{"expressID":1,"type":2077209135,"Identification":null,"FamilyName":null,"GivenName":{"value":"","type":1,"name":"IFCLABEL"},"MiddleNames":null,"PrefixTitles":null,"SuffixTitles":null,"Roles":null,"Addresses":null},"TheOrganization":{"expressID":2,"type":4251960020,"Identification":null,"Name":{"value":"","type":1,"name":"IFCLABEL"},"Description":null,"Roles":null,"Addresses":null},"Roles":null},"OwningApplication":{"expressID":4,"type":639542469,"ApplicationDeveloper":{"expressID":2,"type":4251960020,"Identification":null,"Name":{"value":"","type":1,"name":"IFCLABEL"},"Description":null,"Roles":null,"Addresses":null},"Version":{"value":"0.21 build 2","type":1,"name":"IFCLABEL"},"ApplicationFullName":{"value":"FreeCAD","type":1,"name":"IFCLABEL"},"ApplicationIdentifier":{"value":"118df2cf_ed21_438e_a41","type":1,"name":"IFCIDENTIFIER"}},"State":null,"ChangeAction":{"type":3,"value":"ADDED"},"LastModifiedDate":{"type":10,"name":"IFCTIMESTAMP","value":1722771575},"LastModifyingUser":{"expressID":3,"type":101040310,"ThePerson":{"expressID":1,"type":2077209135,"Identification":null,"FamilyName":null,"GivenName":{"value":"","type":1,"name":"IFCLABEL"},"MiddleNames":null,"PrefixTitles":null,"SuffixTitles":null,"Roles":null,"Addresses":null},"TheOrganization":{"expressID":2,"type":4251960020,"Identification":null,"Name":{"value":"","type":1,"name":"IFCLABEL"},"Description":null,"Roles":null,"Addresses":null},"Roles":null},"LastModifyingApplication":{"expressID":4,"type":639542469,"ApplicationDeveloper":{"expressID":2,"type":4251960020,"Identification":null,"Name":{"value":"","type":1,"name":"IFCLABEL"},"Description":null,"Roles":null,"Addresses":null},"Version":{"value":"0.21 build 2","type":1,"name":"IFCLABEL"},"ApplicationFullName":{"value":"FreeCAD","type":1,"name":"IFCLABEL"},"ApplicationIdentifier":{"value":"118df2cf_ed21_438e_a41","type":1,"name":"IFCIDENTIFIER"}},"CreationDate":{"type":10,"name":"IFCTIMESTAMP","value":1722771575}},"Name":{"value":"Unnamed1","type":1,"name":"IFCLABEL"},"Description":null,"ObjectType":null,"LongName":null,"Phase":null,"RepresentationContexts":[{"expressID":21,"type":3448662350,"ContextIdentifier":null,"ContextType":{"value":"Model","type":1,"name":"IFCLABEL"},"CoordinateSpaceDimension":{"type":10,"name":"IFCDIMENSIONCOUNT","value":3},"Precision":{"type":4,"name":"IFCREAL","value":0.00001},"WorldCoordinateSystem":{"expressID":9,"type":2740243338,"Location":{"expressID":8,"type":1123145078,"Coordinates":[{"type":4,"name":"IFCLENGTHMEASURE","value":0},{"type":4,"name":"IFCLENGTHMEASURE","value":0},{"type":4,"name":"IFCLENGTHMEASURE","value":0}]},"Axis":{"expressID":7,"type":32440307,"DirectionRatios":[{"type":4,"name":"IFCREAL","value":0},{"type":4,"name":"IFCREAL","value":0},{"type":4,"name":"IFCREAL","value":1}]},"RefDirection":{"expressID":6,"type":32440307,"DirectionRatios":[{"type":4,"name":"IFCREAL","value":1},{"type":4,"name":"IFCREAL","value":0},{"type":4,"name":"IFCREAL","value":0}]}},"TrueNorth":{"expressID":20,"type":32440307,"DirectionRatios":[{"type":4,"name":"IFCREAL","value":0},{"type":4,"name":"IFCREAL","value":1}]}}],"UnitsInContext":{"expressID":19,"type":180925521,"Units":[{"expressID":13,"type":448429030,"Dimensions":{"value":0,"type":5},"UnitType":{"type":3,"value":"LENGTHUNIT"},"Prefix":null,"Name":{"type":3,"value":"METRE"}},{"expressID":14,"type":448429030,"Dimensions":{"value":0,"type":5},"UnitType":{"type":3,"value":"AREAUNIT"},"Prefix":null,"Name":{"type":3,"value":"SQUARE_METRE"}},{"expressID":15,"type":448429030,"Dimensions":{"value":0,"type":5},"UnitType":{"type":3,"value":"VOLUMEUNIT"},"Prefix":null,"Name":{"type":3,"value":"CUBIC_METRE"}},{"expressID":18,"type":2889183280,"Dimensions":{"expressID":12,"type":2949456006,"LengthExponent":0,"MassExponent":0,"TimeExponent":0,"ElectricCurrentExponent":0,"ThermodynamicTemperatureExponent":0,"AmountOfSubstanceExponent":0,"LuminousIntensityExponent":0},"UnitType":{"type":3,"value":"PLANEANGLEUNIT"},"Name":{"value":"DEGREE","type":1,"name":"IFCLABEL"},"ConversionFactor":{"expressID":17,"type":2597039031,"ValueComponent":{"type":4,"name":"IFCPLANEANGLEMEASURE","value":0.017453292519943295},"UnitComponent":{"expressID":16,"type":448429030,"Dimensions":{"value":0,"type":5},"UnitType":{"type":3,"value":"PLANEANGLEUNIT"},"Prefix":null,"Name":{"type":3,"value":"RADIAN"}}}}]}},"26":{"expressID":26,"type":2515109513,"GlobalId":{"value":"3UVHJYao56mBG6o$k4X87p","type":1,"name":"IFCGLOBALLYUNIQUEID"},"OwnerHistory":{"value":5,"type":5},"Name":{"value":"Structural Analysis Model","type":1,"name":"IFCLABEL"},"Description":null,"ObjectType":null,"PredefinedType":{"type":3,"value":"NOTDEFINED"},"OrientationOf2DPlane":null,"LoadedBy":null,"HasResults":null,"SharedPlacement":{"value":25,"type":5}},"27":{"expressID":27,"type":2565941209,"GlobalId":{"value":"1DSZ3D$ezFiQsDZCTXyt8X","type":1,"name":"IFCGLOBALLYUNIQUEID"},"OwnerHistory":{"value":5,"type":5},"Name":null,"Description":null,"RelatingContext":{"value":23,"type":5},"RelatedDefinitions":[{"value":26,"type":5}]},"330":{"expressID":330,"type":1999602285,"GlobalId":{"value":"2HR69PWiL6XeqNTGjTCh7f","type":1,"name":"IFCGLOBALLYUNIQUEID"},"OwnerHistory":{"value":5,"type":5},"Name":{"value":"Komponente","type":1,"name":"IFCLABEL"},"Description":{"value":"","type":1,"name":"IFCTEXT"},"ObjectType":null,"ObjectPlacement":{"value":25,"type":5},"Representation":{"value":329,"type":5},"Tag":null,"PredefinedType":{"type":3,"value":"CONVECTOR"}},"331":{"expressID":331,"type":3650150729,"Name":{"value":"Baujahr","type":1,"name":"IFCIDENTIFIER"},"Description":null,"NominalValue":{"value":"2018-06-01","type":1,"name":"IFCLABEL"},"Unit":null},"332":{"expressID":332,"type":3650150729,"Name":{"value":"Bauteil","type":1,"name":"IFCIDENTIFIER"},"Description":null,"NominalValue":{"value":"Sammler","type":1,"name":"IFCLABEL"},"Unit":null},"333":{"expressID":333,"type":3650150729,"Name":{"value":"Bauteilgruppe","type":1,"name":"IFCIDENTIFIER"},"Description":null,"NominalValue":{"value":"Decke","type":1,"name":"IFCLABEL"},"Unit":null},"334":{"expressID":334,"type":3650150729,"Name":{"value":"Format","type":1,"name":"IFCIDENTIFIER"},"Description":null,"NominalValue":{"value":"SiC- Beton 70","type":1,"name":"IFCLABEL"},"Unit":null},"335":{"expressID":335,"type":3650150729,"Name":{"value":"Haltbarkeit","type":1,"name":"IFCIDENTIFIER"},"Description":null,"NominalValue":{"value":"12","type":1,"name":"IFCLABEL"},"Unit":null},"336":{"expressID":336,"type":3650150729,"Name":{"value":"Material","type":1,"name":"IFCIDENTIFIER"},"Description":null,"NominalValue":{"value":"SiC- Beton 70","type":1,"name":"IFCLABEL"},"Unit":null},"337":{"expressID":337,"type":3650150729,"Name":{"value":"Schicht","type":1,"name":"IFCIDENTIFIER"},"Description":null,"NominalValue":{"value":"Frontschicht","type":1,"name":"IFCLABEL"},"Unit":null},"338":{"expressID":338,"type":3650150729,"Name":{"value":"Verbauart","type":1,"name":"IFCIDENTIFIER"},"Description":null,"NominalValue":{"value":"gegossen","type":1,"name":"IFCLABEL"},"Unit":null},"339":{"expressID":339,"type":1451395588,"GlobalId":{"value":"2rteAVZO5859YZ$uG1uC$_","type":1,"name":"IFCGLOBALLYUNIQUEID"},"OwnerHistory":{"value":5,"type":5},"Name":{"value":"Pset_MyCommon","type":1,"name":"IFCLABEL"},"Description":null,"HasProperties":[{"value":331,"type":5},{"value":332,"type":5},{"value":333,"type":5},{"value":334,"type":5},{"value":335,"type":5},{"value":336,"type":5},{"value":337,"type":5},{"value":338,"type":5}]},"340":{"expressID":340,"type":4186316022,"GlobalId":{"value":"1$pUn6hKz7_vw4QPzgQ0Zy","type":1,"name":"IFCGLOBALLYUNIQUEID"},"OwnerHistory":{"value":5,"type":5},"Name":null,"Description":null,"RelatedObjects":[{"value":330,"type":5}],"RelatingPropertyDefinition":{"value":339,"type":5}},"2197":{"expressID":2197,"type":1999602285,"GlobalId":{"value":"0Z74ohIn9Ar9aCe39Jyy79","type":1,"name":"IFCGLOBALLYUNIQUEID"},"OwnerHistory":{"value":5,"type":5},"Name":{"value":"Komponente001","type":1,"name":"IFCLABEL"},"Description":{"value":"","type":1,"name":"IFCTEXT"},"ObjectType":null,"ObjectPlacement":{"value":25,"type":5},"Representation":{"value":2196,"type":5},"Tag":null,"PredefinedType":{"type":3,"value":"CONVECTOR"}},"2198":{"expressID":2198,"type":3650150729,"Name":{"value":"Bauteil","type":1,"name":"IFCIDENTIFIER"},"Description":null,"NominalValue":{"value":"Betonwand","type":1,"name":"IFCLABEL"},"Unit":null},"2199":{"expressID":2199,"type":3650150729,"Name":{"value":"Bauteilgruppe","type":1,"name":"IFCIDENTIFIER"},"Description":null,"NominalValue":{"value":"Todraum","type":1,"name":"IFCLABEL"},"Unit":null},"2200":{"expressID":2200,"type":3650150729,"Name":{"value":"Material","type":1,"name":"IFCIDENTIFIER"},"Description":null,"NominalValue":{"value":"SiC-Beton","type":1,"name":"IFCLABEL"},"Unit":null},"2201":{"expressID":2201,"type":3650150729,"Name":{"value":"Verbauart","type":1,"name":"IFCIDENTIFIER"},"Description":null,"NominalValue":{"value":"gegeossen","type":1,"name":"IFCLABEL"},"Unit":null},"2202":{"expressID":2202,"type":1451395588,"GlobalId":{"value":"1Yfhf0GBzE$PhukmaJzsrr","type":1,"name":"IFCGLOBALLYUNIQUEID"},"OwnerHistory":{"value":5,"type":5},"Name":{"value":"Pset_MyCommon","type":1,"name":"IFCLABEL"},"Description":null,"HasProperties":[{"value":331,"type":5},{"value":2198,"type":5},{"value":2199,"type":5},{"value":335,"type":5},{"value":2200,"type":5},{"value":337,"type":5},{"value":2201,"type":5}]},"2203":{"expressID":2203,"type":4186316022,"GlobalId":{"value":"1MFjL1VAv38uWprSDM0v3W","type":1,"name":"IFCGLOBALLYUNIQUEID"},"OwnerHistory":{"value":5,"type":5},"Name":null,"Description":null,"RelatedObjects":[{"value":2197,"type":5}],"RelatingPropertyDefinition":{"value":2202,"type":5}},"20742":{"expressID":20742,"type":1999602285,"GlobalId":{"value":"1cAfPgRnf4jeHGW0$sjPEO","type":1,"name":"IFCGLOBALLYUNIQUEID"},"OwnerHistory":{"value":5,"type":5},"Name":{"value":"Komponente002","type":1,"name":"IFCLABEL"},"Description":{"value":"","type":1,"name":"IFCTEXT"},"ObjectType":null,"ObjectPlacement":{"value":25,"type":5},"Representation":{"value":20741,"type":5},"Tag":null,"PredefinedType":{"type":3,"value":"CONVECTOR"}},"20743":{"expressID":20743,"type":3650150729,"Name":{"value":"Bauteil","type":1,"name":"IFCIDENTIFIER"},"Description":null,"NominalValue":{"value":"Betondecke","type":1,"name":"IFCLABEL"},"Unit":null},"20744":{"expressID":20744,"type":3650150729,"Name":{"value":"Verbauart","type":1,"name":"IFCIDENTIFIER"},"Description":null,"NominalValue":{"value":"gespritzt","type":1,"name":"IFCLABEL"},"Unit":null},"20745":{"expressID":20745,"type":1451395588,"GlobalId":{"value":"3GB4Jly4z9KAd1CsnhCMIo","type":1,"name":"IFCGLOBALLYUNIQUEID"},"OwnerHistory":{"value":5,"type":5},"Name":{"value":"Pset_MyCommon","type":1,"name":"IFCLABEL"},"Description":null,"HasProperties":[{"value":331,"type":5},{"value":20743,"type":5},{"value":2199,"type":5},{"value":335,"type":5},{"value":2200,"type":5},{"value":337,"type":5},{"value":20744,"type":5}]},"20746":{"expressID":20746,"type":4186316022,"GlobalId":{"value":"0dUGPkdyHDfeL8KFqmnzR$","type":1,"name":"IFCGLOBALLYUNIQUEID"},"OwnerHistory":{"value":5,"type":5},"Name":null,"Description":null,"RelatedObjects":[{"value":20742,"type":5}],"RelatingPropertyDefinition":{"value":20745,"type":5}},"20747":{"expressID":20747,"type":160246688,"GlobalId":{"value":"0G$myakpn8CPE8L95S9WK2","type":1,"name":"IFCGLOBALLYUNIQUEID"},"OwnerHistory":{"value":5,"type":5},"Name":{"value":"ProjectLink","type":1,"name":"IFCLABEL"},"Description":{"value":"","type":1,"name":"IFCTEXT"},"RelatingObject":{"value":23,"type":5},"RelatedObjects":[{"value":330,"type":5},{"value":2197,"type":5},{"value":20742,"type":5}]},"20748":{"expressID":20748,"type":1838606355,"Name":{"value":"SiC-Beton SF","type":1,"name":"IFCLABEL"},"Description":null,"Category":null},"20751":{"expressID":20751,"type":2022407955,"Name":null,"Description":null,"Representations":[{"value":20750,"type":5}],"RepresentedMaterial":{"value":20748,"type":5}},"20752":{"expressID":20752,"type":2655215786,"GlobalId":{"value":"1fORr_8w54YeQth9h5d513","type":1,"name":"IFCGLOBALLYUNIQUEID"},"OwnerHistory":{"value":5,"type":5},"Name":{"value":"MaterialLink","type":1,"name":"IFCLABEL"},"Description":{"value":"","type":1,"name":"IFCTEXT"},"RelatedObjects":[{"value":330,"type":5},{"value":2197,"type":5},{"value":20742,"type":5}],"RelatingMaterial":{"value":20748,"type":5}}}